Workbook

Sheet 1. PORTADA
B2: LESTRAL CONSTRUCTORA Electromecánica del Pacífico (EMP)
B5: PROYECTOS INDUSTRIALES LLAVE EN MANO • INGENIERÍA + CONSTRUCCIÓN + INSTALACIÓN
B7: PROPUESTA DE CONSTRUCCIÓN LLAVE EN MANO REMODELACIÓN DE NAVE CON CUARTO LIMPIO
B9: Proyecto de Remodelación de Nave QMX México • Baja California, México
B11: CLIENTE | C11: QMX / QIUSHI
B12: PROYECTO | C12: Proyecto de Remodelación de Nave con Cuarto Limpio, México
B13: SITIO | C13: Baja California, México
B14: BASE DE LA COTIZACIÓN | C14: Proyecto ejecutivo y catálogo de cantidades del 10-sep-2026 (paquete IFC de Shanghai Jingdian)
B15: No. DE COTIZACIÓN | C15: EMP-QMX-2026-09-CR • Rev. D
B16: FECHA | C16: 10 de septiembre de 2026
B17: VIGENCIA | C17: 30 días naturales
B18: MONEDA | C18: Dólares americanos (USD)
B19: PLAZO DE EJECUCIÓN | C19: 24 semanas a partir del anticipo
B20: PRESENTA | C20: ING. RODRIGO NUÑEZ LOUBET
B22: PRECIO TOTAL DE CONSTRUCCIÓN LLAVE EN MANO (IVA INCLUIDO)
B23: ='6. RESUMEN DE COSTOS'!D21 -> 2369001.8
B25: PROPUESTA CONFIDENCIAL • Elaborada exclusivamente para QMX • Blvd. Insurgentes, Tijuana, Baja California, México Un solo punto de responsabilidad • Ingeniería, procura, construcción y puesta en servicio bajo un mismo contrato Este documento sustituye a la propuesta EMP-QMX-2026-08-F1 Rev. C.1 en el alcance cubierto por el proyecto ejecutivo del 10-sep-2026.

Sheet 2. RESUMEN EJECUTIVO
A1: LESTRAL CONSTRUCTORA, S. DE R.L. DE C.V. | ELECTROMECÁNICA DEL PACÍFICO (EMP)
A2: 2. RESUMEN EJECUTIVO
B4: Lestral Constructora / Electromecánica del Pacífico (EMP) presenta esta propuesta de construcción llave en mano para la remodelación de la nave QMX en Baja California, México, que comprende un ambiente controlado de clase ISO junto con sus áreas de apoyo de producción, inspección, vestidor, transferencia y oficinas. La propuesta fue cotizada partida por partida contra el proyecto ejecutivo emitido el 10 de septiembre de 2026 por Shanghai Jingdian Planning & Architectural Design: planos de arquitectura, estructura, HVAC, hidrosanitario, eléctrico, protección contra incendio y aire comprimido, junto con el catálogo de cantidades del mismo paquete. Todas las cantidades de esta cotización se toman directamente de ese catálogo, unidad por unidad, de manera que la oferta pueda compararse contra el documento del propio cliente sin necesidad de recuantificar. El alcance cubre ocho disciplinas y 341 partidas cotizadas: preliminares y medidas de construcción; arquitectónico, estructura metálica y acabados; HVAC y sistemas de aire de cuarto limpio; instalaciones eléctricas; hidráulica, agua potable y drenaje; protección contra incendio y alarma; sistemas de TI, CCTV y control de acceso; y distribución de aire comprimido. EMP actúa como un solo punto de responsabilidad para la adecuación de ingeniería, la procura, la construcción, las pruebas y la puesta en servicio. Dos asuntos requieren la atención del cliente y se desarrollan en la sección de Ingeniería de Valor. Primero, el diseño especifica equipos a 380 V trifásicos, que no es una tensión de distribución disponible en México; el catálogo lo resuelve con un transformador reductor de 200 kVA, pero reespecificar los equipos a 480/277-220 V elimina por completo el transformador. Segundo, el diseño de protección contra incendio sigue normas chinas GB; tanto la aprobación de la autoridad mexicana como el seguro de planta trabajan con NFPA. EMP cotizó el proyecto exactamente como está diseñado y cuantificó ambas alternativas por separado para que el cliente decida con elementos.
B20: COSTO POR DISCIPLINA
B21: DISCIPLINA | C21: PARTIDAS | D21: COSTO DIRECTO (USD) | E21: % DEL DIRECTO
B22: 01 PRELIMINARES Y MEDIDAS DE CONSTRUCCIÓN | C22: 22 | D22: =SUMIF('5. DESGLOSE PARTIDAS'!$A:$A,"A TOTAL",'5. DESGLOSE PARTIDAS'!$H:$H) -> 266800 | E22: =IF($D$30=0,0,D22/$D$30) -> 0.14883253
B23: 02 ARQUITECTÓNICO, ESTRUCTURA Y ACABADOS | C23: 31 | D23: =SUMIF('5. DESGLOSE PARTIDAS'!$A:$A,"B TOTAL",'5. DESGLOSE PARTIDAS'!$H:$H) -> 606786.77 | E23: =IF($D$30=0,0,D23/$D$30) -> 0.33849179
B24: 03 HVAC Y SISTEMAS DE AIRE DE CUARTO LIMPIO | C24: 111 | D24: =SUMIF('5. DESGLOSE PARTIDAS'!$A:$A,"C TOTAL",'5. DESGLOSE PARTIDAS'!$H:$H) -> 365367 | E24: =IF($D$30=0,0,D24/$D$30) -> 0.20381745
B25: 04 INSTALACIONES ELÉCTRICAS | C25: 63 | D25: =SUMIF('5. DESGLOSE PARTIDAS'!$A:$A,"D TOTAL",'5. DESGLOSE PARTIDAS'!$H:$H) -> 275378.78 | E25: =IF($D$30=0,0,D25/$D$30) -> 0.15361814
B26: 05 HIDRÁULICA, AGUA POTABLE Y DRENAJE | C26: 35 | D26: =SUMIF('5. DESGLOSE PARTIDAS'!$A:$A,"E TOTAL",'5. DESGLOSE PARTIDAS'!$H:$H) -> 62252.99 | E26: =IF($D$30=0,0,D26/$D$30) -> 0.034727399
B27: 06 PROTECCIÓN CONTRA INCENDIO Y ALARMA | C27: 51 | D27: =SUMIF('5. DESGLOSE PARTIDAS'!$A:$A,"F TOTAL",'5. DESGLOSE PARTIDAS'!$H:$H) -> 150728.24 | E27: =IF($D$30=0,0,D27/$D$30) -> 0.084082703
B28: 07 SISTEMAS DE TI, CCTV Y CONTROL DE ACCESO | C28: 20 | D28: =SUMIF('5. DESGLOSE PARTIDAS'!$A:$A,"G TOTAL",'5. DESGLOSE PARTIDAS'!$H:$H) -> 34987.99 | E28: =IF($D$30=0,0,D28/$D$30) -> 0.019517808
B29: 08 DISTRIBUCIÓN DE AIRE COMPRIMIDO | C29: 8 | D29: =SUMIF('5. DESGLOSE PARTIDAS'!$A:$A,"H TOTAL",'5. DESGLOSE PARTIDAS'!$H:$H) -> 30317.09 | E29: =IF($D$30=0,0,D29/$D$30) -> 0.016912178
B30: COSTO DIRECTO TOTAL | C30: =SUM(C22:C29) -> 341 | D30: =SUM(D22:D29) -> 1792618.9 | E30: 1
B32: Precio total antes de IVA | C32: ='6. RESUMEN DE COSTOS'!D19 -> 2193520.1
B33: Precio total con IVA 8% | C33: ='6. RESUMEN DE COSTOS'!D21 -> 2369001.8
B34: Plazo de ejecución (semanas) | C34: 24
B35: Ahorro identificado por ingeniería de valor | C35: ='9. INGENIERIA DE VALOR'!E16 -> 80869.6
B36: Plazo optimizado (semanas) | C36: 20

Sheet 3. ALCANCE DEL TRABAJO
A1: LESTRAL CONSTRUCTORA, S. DE R.L. DE C.V. | ELECTROMECÁNICA DEL PACÍFICO (EMP)
A2: 3. ALCANCE DEL TRABAJO DETALLADO POR SISTEMA Y DISCIPLINA
B4: El alcance siguiente es la descripción contractual de los trabajos. Corresponde partida por partida al catálogo cotizado de la hoja 5 y al proyecto ejecutivo emitido el 10-sep-2026.
B6: A. PRELIMINARES Y MEDIDAS DE CONSTRUCCIÓN
B7: ▪ | C7: Administración de obra, superintendencia, coordinación de seguridad y administración de campo durante todo el plazo.
B8: ▪ | C8: Instalaciones provisionales, andamios, maniobras de izaje, servicios temporales, herramienta menor y limpieza de obra.
B9: ▪ | C9: Planos de taller, adecuación del paquete IFC a normativa mexicana (NOM-001-SEDE-2012, NOM-002-STPS-2010, referencias NFPA) y elaboración de planos as-built.
B10: ▪ | C10: Trazo, niveles y levantamiento; muestras, prototipos y pruebas de laboratorio; supervisión de calidad bajo plan de inspección y pruebas.
B11: ▪ | C11: Seguros y cuotas obligatorias, protección de obra terminada, reporte diario de avance con registro fotográfico.
B12: ▪ | C12: Pruebas de calidad de aire interior a la terminación y pruebas, verificación y visto bueno de protección contra incendio ante autoridad.
B14: B. ARQUITECTÓNICO, ESTRUCTURA Y ACABADOS
B15: ▪ | C15: Estructura metálica: columnas, vigas, largueros, tensores, puntales, escaleras, placas ahogadas y tornillería de alta resistencia, con primario de taller y montaje.
B16: ▪ | C16: Envolvente de cuarto limpio en panel sándwich de lana mineral de 50 mm con perfilería de aluminio y juntas totalmente selladas, incluye plafón transitable.
B17: ▪ | C17: Muros de block ligero con repellado, anclaje, refuerzo, dalas y dinteles; malla de cerramiento.
B18: ▪ | C18: Pisos: sistema epóxico disipativo con retícula de cobre sobre mortero epóxico, epóxico bicomponente estándar, loseta antiderrapante sobre impermeabilizante de poliuretano.
B19: ▪ | C19: Puertas de cuarto limpio (dos hojas, una hoja y corrediza) con herrajes completos; ventanas de observación en cristal templado; puertas de baño en chapa de madera.
B20: ▪ | C20: Acabado de baños: azulejo en muro y piso, plafón de aluminio, cubierta de lavabo en mármol, espejo con marco, mamparas, barras de apoyo y accesorios.
B21: ▪ | C21: Demolición de baños, muros divisorios y plafones existentes, con reparación de piso igualando el acabado contiguo.
B23: C. HVAC Y SISTEMAS DE AIRE DE CUARTO LIMPIO
B24: ▪ | C24: Aire acondicionado de cuarto limpio: fan coils de alta presión estática alimentados por una unidad condensadora exterior de 123.5 kW, con termostatos, distribuidores refnet y distribución completa de refrigerante.
B25: ▪ | C25: Aire exterior de cuarto limpio: unidad manejadora de expansión directa de 2,500 m3/h a 300 Pa de presión estática externa con su sección condensadora exterior, compuertas motorizadas y manuales, y manómetros diferenciales para la cascada de presión.
B26: ▪ | C26: Climatización de áreas no clasificadas: unidades interiores multi-split tipo cassette de cuatro vías alimentadas por una condensadora de 33.5 kW, y recuperador de calor total para aire exterior.
B27: ▪ | C27: Ventilación y extracción: ventiladores centrífugos en línea y tipo gabinete, extractores de baño, unidad de filtración de carbón activado para extracción de proceso, celosías a prueba de lluvia y sombreretes.
B28: ▪ | C28: Ducto de lámina galvanizada fabricado e instalado con clase de hermeticidad conforme a GB 50243-2016 / equivalente SMACNA, con aislamiento elastomérico clase B1 y conexiones flexibles de lona.
B29: ▪ | C29: Columnas de retorno, soportería, drenaje de condensados en UPVC, carga adicional de refrigerante y todos los accesorios de tubería.
B30: ▪ | C30: Sistema de control automático del HVAC de cuarto limpio: controladores, sensores de campo, cableado, programación y puesta en marcha.
B31: ▪ | C31: Pruebas, ajuste y balanceo de todos los sistemas de aire, con resultados documentados por zona.
B33: D. INSTALACIONES ELÉCTRICAS
B34: ▪ | C34: Transformador seco tipo interior de 200 kVA, primario 480 V / secundario 380 V, con base y conexiones, según proyecto ejecutivo.
B35: ▪ | C35: Ocho tableros de distribución (1APZ, 1AL1, 1AP-KT, 2AC-KT1, 2AC-KT2, 1AC-PW1, 1AC-PW2, 1ALED) según diagrama unifilar, con interruptores y conexiones, más la adecuación de tableros existentes afectados por el nuevo layout.
B36: ▪ | C36: Charola galvanizada por inmersión en caliente tipo escalera y tipo canal con puentes de continuidad; sistemas de tubería conduit de acero ocultos en plenum de plafón.
B37: ▪ | C37: Cableado de fuerza en cobre con aislamiento XLPE libre de halógenos, desde 3x4 mm2 hasta 4x150+1x70 mm2, con terminales tipo seco interior.
B38: ▪ | C38: Alumbrado: luminarios LED tipo panel plano sobreponer y empotrados, luminarios de emergencia con respaldo de batería, señales luminosas direccionales y de salida.
B39: ▪ | C39: Apagadores, contactos de seguridad incluyendo tipo intemperie, cajas de conexión y todas las conexiones finales.
B40: ▪ | C40: Puesta a tierra y equipotencialidad: cajas de equipotencialidad suplementaria, solera galvanizada, conductores de tierra en tubo, con medición de resistencia y certificación.
B41: ▪ | C41: Puesta en servicio del sistema de distribución menor a 1 kV y desmantelamiento de instalaciones eléctricas existentes.
B43: E. HIDRÁULICA, AGUA POTABLE Y DRENAJE
B44: ▪ | C44: Muebles sanitarios: inodoros, mingitorios con fluxómetro de sensor, lavabos bajo cubierta con mezcladora y vertedero de aseo.
B45: ▪ | C45: Distribución de agua potable en PP-R de De20 a De40, oculta en plenum de plafón y ahogada en muro.
B46: ▪ | C46: Drenaje sanitario: colector de acero galvanizado con recubrimiento epóxico interior De110 y ramales de PVC De110, De75 y De50, con coladeras y registros de limpieza.
B47: ▪ | C47: Válvulas y especialidades: válvulas de compuerta de bronce y de fierro, válvulas check, juntas flexibles de hule, manómetro y rompedor de vacío.
B48: ▪ | C48: Estación integral de bombeo de aguas residuales con dos bombas de 10 m3/h a 20 m de carga y tablero de control, más una bomba de 3.6 m3/h con su tablero.
B49: ▪ | C49: Excavación, relleno, restitución de losa y ranurado en muro para tubería enterrada y oculta, con sellado cortafuego en todas las penetraciones.
B50: ▪ | C50: Prueba de presión, prueba de hermeticidad y lavado de la instalación completa, y desmantelamiento de tubería y equipo hidrosanitario existente.
B52: F. PROTECCIÓN CONTRA INCENDIO Y ALARMA
B53: ▪ | C53: Sistema de hidrantes: tubería galvanizada por inmersión en caliente DN100 y DN65 con sistema ranurado, cinco gabinetes de hidrante interior completos con válvula, pitón y manguera de 25 m, y ocho gabinetes de extintores con dos extintores cada uno.
B54: ▪ | C54: Sistema de rociadores: tubería galvanizada por inmersión en caliente de DN25 a DN150, 118 rociadores colgantes K=80, válvula de mariposa con supervisión, detector de flujo, purga automática de aire y válvula de prueba del inspector.
B55: ▪ | C55: Arriostramiento sísmico, soportería, sellado cortafuego en todas las penetraciones, y prueba hidrostática, de hermeticidad y lavado de ambos sistemas húmedos.
B56: ▪ | C56: Alarma contra incendio: panel repetidor y de control montado en piso, detectores de humo fotoeléctricos direccionables, dispositivos audibles y visuales, bocinas, estaciones manuales, botones de hidrante y jacks de teléfono de bomberos.
B57: ▪ | C57: Módulos direccionables de entrada, salida y entrada/salida con aisladores de cortocircuito de lazo, en cable resistente al fuego y tubería conduit dedicada.
B58: ▪ | C58: Verificación punto a punto, programación y puesta en servicio del sistema completo de detección y alarma, y desmantelamiento de instalaciones de protección contra incendio existentes.
B60: G. SISTEMAS DE TI, CCTV Y CONTROL DE ACCESO
B61: ▪ | C61: CCTV: ocho cámaras de red tipo bala infrarrojas de interior de 4 MP o superior con amplio rango dinámico y entrada de audio, sobre cableado CAT.6 en charola y tubería dedicadas, integradas con el NVR y servidor existentes.
B62: ▪ | C62: Control de acceso: siete terminales de reconocimiento facial con fuentes conmutadas, chapas magnéticas para puerta sencilla y doble, y botones de salida.
B63: ▪ | C63: Cableado de fuerza blindado y sin blindaje, sistemas de tubería conduit de acero y cajas de conexión para ambos subsistemas.
B64: ▪ | C64: Configuración, integración con el servidor y enrolador existentes del cliente, pruebas funcionales y puesta en servicio.
B65: ▪ | C65: El equipo de cabecera (servidor, switches, NVR y enrolador) se reutiliza de la instalación existente del cliente, según lo indicado en el proyecto ejecutivo.
B67: H. DISTRIBUCIÓN DE AIRE COMPRIMIDO
B68: ▪ | C68: Cabezal principal en acero inoxidable SUS304 DN50 con todos sus accesorios y soportería.
B69: ▪ | C69: Ocho bajadas DN20 con válvulas de corte manual preinstaladas en el cabezal para conexión futura de ramales, a razón de 0.8 m por bajada.
B70: ▪ | C70: Barrenos en muro con sellado cortafuego, prueba de presión, prueba de hermeticidad y purga de líneas.
B71: ▪ | C71: El alcance se limita al cabezal principal y a las válvulas preinstaladas; la tubería de ramales aguas abajo de cada válvula hasta el punto de uso no está incluida, según lo indicado en el proyecto ejecutivo.

Sheet 4. EXCLUSIONES Y SUPUESTOS
A1: LESTRAL CONSTRUCTORA, S. DE R.L. DE C.V. | ELECTROMECÁNICA DEL PACÍFICO (EMP)
A2: 4. EXCLUSIONES, SUPUESTOS Y BASE DEL PRECIO
B4: EXCLUSIONES
B5: 1 | C5: Equipo de proceso y producción, y cualquier conexión de servicio aguas abajo de la válvula preinstalada o caja terminal que deja este contrato.
B6: 2 | C6: Tubería de ramales de aire comprimido aguas abajo de las ocho válvulas DN20 preinstaladas; compresor, secador, tanque y tren de tratamiento de aire.
B7: 3 | C7: Equipo de cabecera de baja tensión: servidor de CCTV, switches, NVR, servidor de control de acceso y enrolador, todos reutilizados de la instalación existente del cliente.
B8: 4 | C8: Mobiliario de oficina, estaciones de trabajo, lockers, gabinetes, lavabos del vestidor y botes de basura, según lo señalado en el catálogo del cliente.
B9: 5 | C9: Generación, almacenamiento y distribución de agua desionizada, purificada o de proceso.
B10: 6 | C10: Permisos, licencias y derechos municipales, estatales y federales; cuotas de conexión y cargos por demanda de la compañía suministradora.
B11: 7 | C11: Ampliación del servicio eléctrico aguas arriba del tablero general existente, incluyendo transformador de la compañía, medición y alimentador primario.
B12: 8 | C12: Refuerzo estructural de la losa, cimentación o cubierta del edificio existente más allá de la estructura metálica indicada en el proyecto ejecutivo.
B13: 9 | C13: Retiro, tratamiento o disposición de materiales peligrosos, asbesto o suelo contaminado que se descubran durante los trabajos.
B14: 10 | C14: Vestimenta de cuarto limpio, consumibles, filtros de repuesto adicionales al primer juego instalado, y capacitación de operadores más allá de la sesión de entrega.
B15: 11 | C15: Honorarios de organismos certificadores externos cuando el cliente decida designar un certificador independiente.
B16: 12 | C16: Impuestos de importación y gastos aduanales sobre equipo suministrado por el cliente.
B18: SUPUESTOS Y BASE DEL PRECIO
B19: 1 | C19: Todas las cantidades se toman del catálogo del cliente del 10-sep-2026 sin recuantificar. Las cantidades quedan sujetas a verificación contra los planos IFC durante la elaboración de planos de taller; las variaciones se liquidan a los precios unitarios de esta cotización.
B20: 2 | C20: Los precios unitarios son firmes por 30 días naturales y se expresan en dólares americanos. Cuando se requiere tipo de cambio de referencia para insumos en pesos, se utilizó 17.00 MXN por USD; el tipo de cambio se reconsidera a la firma del contrato.
B21: 3 | C21: Los precios incluyen material, mano de obra, equipo, herramienta, transporte, supervisión, indirectos de campo y las obligaciones de garantía del contratista, puesto en obra e instalado.
B22: 4 | C22: Acceso libre, seguro y continuo a las áreas de trabajo durante el horario acordado, con frente de trabajo despejado y área de maniobra adecuada dentro de la planta.
B23: 5 | C23: El servicio eléctrico existente tiene capacidad disponible suficiente en el tablero general para alimentar la nueva carga; esto se confirma mediante medición durante las primeras dos semanas y se reporta al cliente.
B24: 6 | C24: El equipo a 380 V especificado en el proyecto ejecutivo se cotiza tal como está diseñado, junto con el transformador reductor de 200 kVA necesario para alimentarlo.
B25: 7 | C25: El sistema de protección contra incendio se cotiza tal como está diseñado bajo normas GB. Se asume que la aprobación de la autoridad mexicana y de la aseguradora de la planta la obtiene el cliente sobre esa base, o bien se adopta la alternativa NFPA de la sección de Ingeniería de Valor.
B26: 8 | C26: La estructura, losa y cubierta del edificio se encuentran en buen estado y son capaces de recibir las nuevas cargas sin refuerzo distinto al indicado en los planos.
B27: 9 | C27: Los trabajos se ejecutan en un solo turno diurno, de lunes a sábado. En preliminares se lleva una provisión de trabajo nocturno y aceleración que se libera si se otorga acceso las 24 horas.
B28: 10 | C28: Aplica IVA del 8% conforme al estímulo fiscal de la Región Fronteriza Norte para Baja California.
B29: 11 | C29: Los cambios de alcance, cantidad o especificación se ejecutan contra orden de cambio firmada, a los precios unitarios aquí establecidos.

Sheet 5. DESGLOSE PARTIDAS
A1: LESTRAL CONSTRUCTORA, S. DE R.L. DE C.V. | ELECTROMECÁNICA DEL PACÍFICO (EMP)
A2: 5. DESGLOSE POR PARTIDAS — TODAS LAS CIFRAS EN USD
A3: CELDAS EDITABLES: columnas E y F (precio unitario de material e instalación), en azul. Todo lo demás está en fórmula y se actualiza automáticamente.
A5: CÓDIGO | B5: DESCRIPCIÓN | C5: UNIDAD | D5: CANTIDAD | E5: P.U. MATERIAL | F5: P.U. INSTALACIÓN | G5: P.U. TOTAL | H5: IMPORTE
A6: SECCIÓN A — 01 PRELIMINARES Y MEDIDAS DE CONSTRUCCIÓN
A7: A-001 | B7: Administración de obra: superintendente, coordinador de seguridad y administración de campo durante todo el periodo de construcción | C7: LOTE | D7: 1 | E7: 0 | F7: 46500 | G7: =E7+F7 -> 46500 | H7: =ROUND(D7*G7,2) -> 46500
A8: A-002 | B8: Instalaciones provisionales: montaje, uso y desmontaje de oficina de obra, almacén, área de cambio y servicios temporales | C8: LOTE | D8: 1 | E8: 0 | F8: 18500 | G8: =E8+F8 -> 18500 | H8: =ROUND(D8*G8,2) -> 18500
A9: A-003 | B9: Medidas de seguridad y vigilancia en obra: señalización, barreras, EPP, guardia contra incendio y control de acceso | C9: LOTE | D9: 1 | E9: 0 | F9: 12500 | G9: =E9+F9 -> 12500 | H9: =ROUND(D9*G9,2) -> 12500
A10: A-004 | B10: Descarga, recepción, resguardo y maniobra interna de equipos y materiales del cliente y del contratista | C10: LOTE | D10: 1 | E10: 0 | F10: 14000 | G10: =E10+F10 -> 14000 | H10: =ROUND(D10*G10,2) -> 14000
A11: A-005 | B11: Andamios y plataformas de trabajo en altura: montaje, desmontaje, renta, transporte y consumibles | C11: LOTE | D11: 1 | E11: 0 | F11: 16500 | G11: =E11+F11 -> 16500 | H11: =ROUND(D11*G11,2) -> 16500
A12: A-006 | B12: Consumo de servicios durante la construcción (energía eléctrica, agua, aire comprimido) | C12: LOTE | D12: 1 | E12: 0 | F12: 9500 | G12: =E12+F12 -> 9500 | H12: =ROUND(D12*G12,2) -> 9500
A13: A-007 | B13: Seguros de personal y equipo: responsabilidad civil, todo riesgo de construcción, IMSS y cuotas obrero-patronales | C13: LOTE | D13: 1 | E13: 0 | F13: 14500 | G13: =E13+F13 -> 14500 | H13: =ROUND(D13*G13,2) -> 14500
A14: A-008 | B14: Maniobras de izaje y grúa requeridas para la colocación de materiales y equipos | C14: LOTE | D14: 1 | E14: 0 | F14: 8500 | G14: =E14+F14 -> 8500 | H14: =ROUND(D14*G14,2) -> 8500
A15: A-009 | B15: Planos de taller, adecuación del paquete IFC a normativa mexicana (NOM-001-SEDE, NOM-002-STPS, NFPA) y elaboración de planos as-built | C15: LOTE | D15: 1 | E15: 0 | F15: 26500 | G15: =E15+F15 -> 26500 | H15: =ROUND(D15*G15,2) -> 26500
A16: A-010 | B16: Acarreo secundario de materiales y transporte interno dentro de la planta | C16: LOTE | D16: 1 | E16: 0 | F16: 6500 | G16: =E16+F16 -> 6500 | H16: =ROUND(D16*G16,2) -> 6500
A17: A-011 | B17: Niveles de proyecto, trazo, ejes y levantamiento topográfico | C17: LOTE | D17: 1 | E17: 0 | F17: 7500 | G17: =E17+F17 -> 7500 | H17: =ROUND(D17*G17,2) -> 7500
A18: A-012 | B18: Reporte diario de avance y registro fotográfico | C18: LOTE | D18: 1 | E18: 0 | F18: 4800 | G18: =E18+F18 -> 4800 | H18: =ROUND(D18*G18,2) -> 4800
... A28: A-022 | B28: Juegos de planos, transmittals y registros de aprobación firmados | C28: LOTE | D28: 1 | E28: 0 | F28: 4200 | G28: =E28+F28 -> 4200 | H28: =ROUND(D28*G28,2) -> 4200
A29: A TOTAL | B29: SUBTOTAL SECCIÓN A — 01 PRELIMINARES Y MEDIDAS DE CONSTRUCCIÓN | H29: =SUM(H7:H28) -> 266800
A31: SECCIÓN B — 02 ARQUITECTÓNICO, ESTRUCTURA Y ACABADOS
A32: B-001 | B32: Columnas de acero 200x200x6 Q235B equivalente ASTM A36/A572, incluye placas base, atiesadores, tornillos grado C y anclas, con primario de taller | C32: TON | D32: 6.386016 | E32: 2350 | F32: 920 | G32: =E32+F32 -> 3270 | H32: =ROUND(D32*G32,2) -> 20882.27
A33: B-002 | B33: Vigas de acero HM244x175x7x11 y HM294x200x8x12 equivalente Q235B, incluye conexiones y primario de taller | C33: TON | D33: 21.728 | E33: 2280 | F33: 880 | G33: =E33+F33 -> 3160 | H33: =ROUND(D33*G33,2) -> 68660.48
A34: B-003 | B34: Largueros, tensores rectos y diagonales, puntales y escaleras: canal, ángulo, tubo rectangular, placa y viga I | C34: TON | D34: 5.926 | E34: 2420 | F34: 1120 | G34: =E34+F34 -> 3540 | H34: =ROUND(D34*G34,2) -> 20978.04
A35: B-004 | B35: Placas e insertos ahogados según planos, incluye limpieza y primario anticorrosivo | C35: TON | D35: 0.994752 | E35: 2650 | F35: 1450 | G35: =E35+F35 -> 4100 | H35: =ROUND(D35*G35,2) -> 4078.48
A36: B-005 | B36: Tornillería estructural de alta resistencia M20 grado 10.9, incluye arandelas y registro de torque | C36: EQ | D36: 388 | E36: 4.6 | F36: 3.1 | G36: =E36+F36 -> 7.7 | H36: =ROUND(D36*G36,2) -> 2987.6
A37: B-006 | B37: Muro de block ligero de 200 mm con repellado de mortero cemento-arena, incluye anclaje, refuerzo, dala, reventón y dinteles | C37: M2 | D37: 159.5 | E37: 23.5 | F37: 29.5 | G37: =E37+F37 -> 53 | H37: =ROUND(D37*G37,2) -> 8453.5
A38: B-007 | B38: Muro de azulejo 300x600 mm en baños, adherido con pegazulejo especial sobre impermeabilizante de poliuretano de 1.5 mm | C38: M2 | D38: 200.8272 | E38: 27 | F38: 25 | G38: =E38+F38 -> 52 | H38: =ROUND(D38*G38,2) -> 10443.01
A39: B-008 | B39: Muro divisorio de panel sándwich para cuarto limpio, núcleo de lana mineral de 50 mm, incluye perfilería de aluminio y sellado total de juntas con silicón | C39: M2 | D39: 1127.992 | E39: 118 | F39: 44 | G39: =E39+F39 -> 162 | H39: =ROUND(D39*G39,2) -> 182734.7
A40: B-009 | B40: Malla de cerramiento con postes de PTR 50 mm a cada 2.5 m, alambre de malla no menor a 2.4 mm, incluye puerta y anclaje a piso | C40: ML | D40: 73.2348 | E40: 49 | F40: 23 | G40: =E40+F40 -> 72 | H40: =ROUND(D40*G40,2) -> 5272.91
A41: B-010 | B41: Piso de loseta antiderrapante 600x600 mm adherida con pegazulejo especial sobre impermeabilizante de poliuretano de 1.5 mm | C41: M2 | D41: 61.803 | E41: 28.5 | F41: 23 | G41: =E41+F41 -> 51.5 | H41: =ROUND(D41*G41,2) -> 3182.85
A42: B-011 | B42: Piedra de umbral incluye adhesivo, preparación de superficie, nivelación, biselado y pulido de canto | C42: M2 | D42: 1.2 | E42: 68 | F42: 32 | G42: =E42+F42 -> 100 | H42: =ROUND(D42*G42,2) -> 120
A43: B-012 | B43: Sistema de piso epóxico disipativo (ESD): primario epóxico, mortero epóxico, mortero epóxico antiestático, retícula de cobre y acabado epóxico | C43: M2 | D43: 646.3275 | E43: 59 | F43: 39 | G43: =E43+F43 -> 98 | H43: =ROUND(D43*G43,2) -> 63340.1
... A62: B-031 | B62: Demolición y reparación: muros, pisos y plafones de baños existentes; otros muros divisorios y plafones; reparación de piso igualando el acabado contiguo | C62: LOTE | D62: 1 | E62: 0 | F62: 29500 | G62: =E62+F62 -> 29500 | H62: =ROUND(D62*G62,2) -> 29500
A63: B TOTAL | B63: SUBTOTAL SECCIÓN B — 02 ARQUITECTÓNICO, ESTRUCTURA Y ACABADOS | H63: =SUM(H32:H62) -> 606786.77
A65: SECCIÓN C — 03 HVAC Y SISTEMAS DE AIRE DE CUARTO LIMPIO
A66: C-001 | B66: Fan coil de alta presión estática, 10.0 kW frío / 11.2 kW calor, 250 W, 1F 220V 60Hz, con bomba de condensados integrada | C66: EQ | D66: 12 | E66: 1180 | F66: 270 | G66: =E66+F66 -> 1450 | H66: =ROUND(D66*G66,2) -> 17400
A67: C-002 | B67: Fan coil de alta presión estática, 12.5 kW frío / 14.0 kW calor, 340 W, 1F 220V 60Hz, con bomba de condensados integrada | C67: EQ | D67: 1 | E67: 1420 | F67: 295 | G67: =E67+F67 -> 1715 | H67: =ROUND(D67*G67,2) -> 1715
A68: C-003 | B68: Unidad interior multi-split tipo cassette de 4 vías, 5.6 kW frío / 6.5 kW calor, 40 W, 1F 220V 60Hz | C68: EQ | D68: 1 | E68: 985 | F68: 225 | G68: =E68+F68 -> 1210 | H68: =ROUND(D68*G68,2) -> 1210
A69: C-004 | B69: Unidad condensadora exterior para el sistema de fan coils, 123.5 kW frío / 137.5 kW calor, 41.57 kW, 3F 60Hz, montada sobre base exterior | C69: EQ | D69: 1 | E69: 36500 | F69: 4300 | G69: =E69+F69 -> 40800 | H69: =ROUND(D69*G69,2) -> 40800
A70: C-005 | B70: Termostato de pared con control de temperatura ambiente | C70: PZA | D70: 14 | E70: 148 | F70: 46 | G70: =E70+F70 -> 194 | H70: =ROUND(D70*G70,2) -> 2716
A71: C-006 | B71: Distribuidor de derivación refnet, tipo E-102SN | C71: PZA | D71: 5 | E71: 168 | F71: 56 | G71: =E71+F71 -> 224 | H71: =ROUND(D71*G71,2) -> 1120
A72: C-007 | B72: Distribuidor de derivación refnet, tipo E-162SN | C72: PZA | D72: 2 | E72: 218 | F72: 66 | G72: =E72+F72 -> 284 | H72: =ROUND(D72*G72,2) -> 568
A73: C-008 | B73: Distribuidor de derivación refnet, tipo E-242SN | C73: PZA | D73: 4 | E73: 288 | F73: 76 | G73: =E73+F73 -> 364 | H73: =ROUND(D73*G73,2) -> 1456
A74: C-009 | B74: Distribuidor de derivación refnet, tipo E-302SN | C74: PZA | D74: 2 | E74: 345 | F74: 86 | G74: =E74+F74 -> 431 | H74: =ROUND(D74*G74,2) -> 862
A75: C-010 | B75: Difusor cuadrado de plafón 350x350 mm | C75: PZA | D75: 12 | E75: 63 | F75: 29 | G75: =E75+F75 -> 92 | H75: =ROUND(D75*G75,2) -> 1104
A76: C-011 | B76: Difusor cuadrado de plafón 500x500 mm | C76: PZA | D76: 7 | E76: 96 | F76: 36 | G76: =E76+F76 -> 132 | H76: =ROUND(D76*G76,2) -> 924
A77: C-012 | B77: Rejilla de una deflexión 800x300 mm | C77: PZA | D77: 13 | E77: 79 | F77: 31 | G77: =E77+F77 -> 110 | H77: =ROUND(D77*G77,2) -> 1430
... A176: C-111 | B176: Desmantelamiento y disposición de ductos, tuberías y equipos de HVAC existentes | C176: LOTE | D176: 1 | E176: 0 | F176: 9800 | G176: =E176+F176 -> 9800 | H176: =ROUND(D176*G176,2) -> 9800
A177: C TOTAL | B177: SUBTOTAL SECCIÓN C — 03 HVAC Y SISTEMAS DE AIRE DE CUARTO LIMPIO | H177: =SUM(H66:H176) -> 365367
A179: SECCIÓN D — 04 INSTALACIONES ELÉCTRICAS
A180: D-001 | B180: Transformador seco tipo interior, 200 kVA, primario 3F 480V 60Hz / secundario 380V 60Hz, devanados de aluminio, incluye base y conexiones | C180: EQ | D180: 1 | E180: 18500 | F180: 2900 | G180: =E180+F180 -> 21400 | H180: =ROUND(D180*G180,2) -> 21400
A181: D-002 | B181: Adecuación y reconexión de tableros de distribución existentes afectados por el nuevo layout | C181: LOTE | D181: 1 | E181: 0 | F181: 6800 | G181: =E181+F181 -> 6800 | H181: =ROUND(D181*G181,2) -> 6800
A182: D-003 | B182: Tablero de distribución 1APZ según diagrama unifilar, montaje en plenum de plafón, incluye interruptores y conexiones | C182: EQ | D182: 1 | E182: 5200 | F182: 880 | G182: =E182+F182 -> 6080 | H182: =ROUND(D182*G182,2) -> 6080
A183: D-004 | B183: Tablero de distribución 1AL1 según diagrama unifilar, montaje sobrepuesto en muro | C183: EQ | D183: 1 | E183: 3800 | F183: 720 | G183: =E183+F183 -> 4520 | H183: =ROUND(D183*G183,2) -> 4520
A184: D-005 | B184: Tablero de distribución 1AP-KT según diagrama unifilar, montaje sobrepuesto en muro | C184: EQ | D184: 1 | E184: 4600 | F184: 800 | G184: =E184+F184 -> 5400 | H184: =ROUND(D184*G184,2) -> 5400
A185: D-006 | B185: Tablero de distribución 2AC-KT1 según diagrama unifilar, montaje sobrepuesto en muro | C185: EQ | D185: 1 | E185: 3400 | F185: 670 | G185: =E185+F185 -> 4070 | H185: =ROUND(D185*G185,2) -> 4070
A186: D-007 | B186: Tablero de distribución 2AC-KT2 según diagrama unifilar, montaje sobrepuesto en muro | C186: EQ | D186: 1 | E186: 3400 | F186: 670 | G186: =E186+F186 -> 4070 | H186: =ROUND(D186*G186,2) -> 4070
A187: D-008 | B187: Tablero de distribución 1AC-PW1 según diagrama unifilar, montaje sobrepuesto en muro | C187: EQ | D187: 1 | E187: 3900 | F187: 720 | G187: =E187+F187 -> 4620 | H187: =ROUND(D187*G187,2) -> 4620
A188: D-009 | B188: Tablero de distribución 1AC-PW2 según diagrama unifilar, montaje sobrepuesto en muro | C188: EQ | D188: 1 | E188: 3900 | F188: 720 | G188: =E188+F188 -> 4620 | H188: =ROUND(D188*G188,2) -> 4620
A189: D-010 | B189: Tablero de distribución 1ALED según diagrama unifilar, montaje sobrepuesto en muro | C189: EQ | D189: 1 | E189: 2900 | F189: 620 | G189: =E189+F189 -> 3520 | H189: =ROUND(D189*G189,2) -> 3520
A190: D-011 | B190: Charola tipo escalera, 400x100x1.5 mm, galvanizada por inmersión en caliente, con puentes de continuidad | C190: ML | D190: 212 | E190: 47 | F190: 23 | G190: =E190+F190 -> 70 | H190: =ROUND(D190*G190,2) -> 14840
A191: D-012 | B191: Charola tipo canal, 200x100x1.2 mm, galvanizada por inmersión en caliente, con puentes de continuidad | C191: ML | D191: 8.47 | E191: 33 | F191: 19 | G191: =E191+F191 -> 52 | H191: =ROUND(D191*G191,2) -> 440.44
... A242: D-063 | B242: Desmantelamiento y disposición de tubería, cableado y equipo eléctrico existente | C242: LOTE | D242: 1 | E242: 0 | F242: 11500 | G242: =E242+F242 -> 11500 | H242: =ROUND(D242*G242,2) -> 11500
A243: D TOTAL | B243: SUBTOTAL SECCIÓN D — 04 INSTALACIONES ELÉCTRICAS | H243: =SUM(H180:H242) -> 275378.78
A245: SECCIÓN E — 05 HIDRÁULICA, AGUA POTABLE Y DRENAJE
A246: E-001 | B246: Inodoro de piso, completo con asiento, alimentación y juego de fijación | C246: EQ | D246: 6 | E246: 330 | F246: 115 | G246: =E246+F246 -> 445 | H246: =ROUND(D246*G246,2) -> 2670
A247: E-002 | B247: Mingitorio de pared con fluxómetro de sensor | C247: EQ | D247: 2 | E247: 495 | F247: 135 | G247: =E247+F247 -> 630 | H247: =ROUND(D247*G247,2) -> 1260
A248: E-003 | B248: Lavabo bajo cubierta con mezcladora de agua fría y caliente | C248: EQ | D248: 3 | E248: 295 | F248: 125 | G248: =E248+F248 -> 420 | H248: =ROUND(D248*G248,2) -> 1260
A249: E-004 | B249: Vertedero de aseo con llave de pared | C249: EQ | D249: 1 | E249: 270 | F249: 105 | G249: =E249+F249 -> 375 | H249: =ROUND(D249*G249,2) -> 375
A250: E-005 | B250: Tubería de agua potable PP-R, De40, oculta en plenum de plafón | C250: ML | D250: 11.385 | E250: 9.8 | F250: 8.8 | G250: =E250+F250 -> 18.6 | H250: =ROUND(D250*G250,2) -> 211.76
A251: E-006 | B251: Tubería de agua potable PP-R, De32, oculta en plenum de plafón | C251: ML | D251: 5.421856 | E251: 7.4 | F251: 7.8 | G251: =E251+F251 -> 15.2 | H251: =ROUND(D251*G251,2) -> 82.41
A252: E-007 | B252: Tubería de agua potable PP-R, De25, oculta en plenum de plafón | C252: ML | D252: 12.265 | E252: 5.6 | F252: 7 | G252: =E252+F252 -> 12.6 | H252: =ROUND(D252*G252,2) -> 154.54
A253: E-008 | B253: Tubería de agua potable PP-R, De20, oculta en plenum de plafón | C253: ML | D253: 2.64 | E253: 4.3 | F253: 6.4 | G253: =E253+F253 -> 10.7 | H253: =ROUND(D253*G253,2) -> 28.25
A254: E-009 | B254: Tubería de agua potable PP-R, De20, ahogada en muro | C254: ML | D254: 33 | E254: 4.3 | F254: 9.8 | G254: =E254+F254 -> 14.1 | H254: =ROUND(D254*G254,2) -> 465.3
A255: E-010 | B255: Tubería de acero galvanizado con recubrimiento epóxico interior, De110, para colector sanitario | C255: ML | D255: 78 | E255: 43 | F255: 23 | G255: =E255+F255 -> 66 | H255: =ROUND(D255*G255,2) -> 5148
A256: E-011 | B256: Tubería de drenaje PVC, De110 | C256: ML | D256: 12 | E256: 12.8 | F256: 11.5 | G256: =E256+F256 -> 24.3 | H256: =ROUND(D256*G256,2) -> 291.6
A257: E-012 | B257: Tubería de drenaje PVC, De75 | C257: ML | D257: 22.89375 | E257: 8.8 | F257: 9.8 | G257: =E257+F257 -> 18.6 | H257: =ROUND(D257*G257,2) -> 425.82
... A280: E-035 | B280: Desmantelamiento y disposición de tubería y equipo hidrosanitario existente | C280: LOTE | D280: 1 | E280: 0 | F280: 6800 | G280: =E280+F280 -> 6800 | H280: =ROUND(D280*G280,2) -> 6800
A281: E TOTAL | B281: SUBTOTAL SECCIÓN E — 05 HIDRÁULICA, AGUA POTABLE Y DRENAJE | H281: =SUM(H246:H280) -> 62252.99
A283: SECCIÓN F — 06 PROTECCIÓN CONTRA INCENDIO Y ALARMA
A284: F-001 | B284: Tubería de acero galvanizado por inmersión en caliente, DN100, sistema de acoplamiento ranurado | C284: ML | D284: 200 | E284: 35 | F284: 27 | G284: =E284+F284 -> 62 | H284: =ROUND(D284*G284,2) -> 12400
A285: F-002 | B285: Tubería de acero galvanizado por inmersión en caliente, DN65, sistema de acoplamiento ranurado | C285: ML | D285: 41.492 | E285: 23 | F285: 21 | G285: =E285+F285 -> 44 | H285: =ROUND(D285*G285,2) -> 1825.65
A286: F-003 | B286: Accesorios de tubería: coples, codos, tes y accesorios para el sistema de hidrantes | C286: LOTE | D286: 1 | E286: 9500 | F286: 0 | G286: =E286+F286 -> 9500 | H286: =ROUND(D286*G286,2) -> 9500
A287: F-004 | B287: Gabinete de hidrante interior con válvula SN65, pitón de 19 mm, manguera de 25 m con forro de hule y válvula de compuerta DN65 | C287: EQ | D287: 5 | E287: 640 | F287: 230 | G287: =E287+F287 -> 870 | H287: =ROUND(D287*G287,2) -> 4350
A288: F-005 | B288: Gabinete de extintores completo con dos extintores MT7 | C288: PZA | D288: 8 | E288: 215 | F288: 68 | G288: =E288+F288 -> 283 | H288: =ROUND(D288*G288,2) -> 2264
A289: F-006 | B289: Válvula de mariposa, DN100, conexión brida ranurada | C289: PZA | D289: 4 | E289: 295 | F289: 98 | G289: =E289+F289 -> 393 | H289: =ROUND(D289*G289,2) -> 1572
A290: F-007 | B290: Válvula de mariposa, DN65, conexión brida ranurada | C290: PZA | D290: 3 | E290: 190 | F290: 73 | G290: =E290+F290 -> 263 | H290: =ROUND(D290*G290,2) -> 789
A291: F-008 | B291: Barrenos en muro y reparación para el sistema de hidrantes | C291: LOTE | D291: 1 | E291: 0 | F291: 3200 | G291: =E291+F291 -> 3200 | H291: =ROUND(D291*G291,2) -> 3200
A292: F-009 | B292: Fabricación e instalación de soportería metálica, incluye limpieza y pintura | C292: KG | D292: 156.33525 | E292: 2.7 | F292: 2.35 | G292: =E292+F292 -> 5.05 | H292: =ROUND(D292*G292,2) -> 789.49
A293: F-010 | B293: Ranurado en piso y muro, barrenos y sellado cortafuego | C293: LOTE | D293: 1 | E293: 0 | F293: 2800 | G293: =E293+F293 -> 2800 | H293: =ROUND(D293*G293,2) -> 2800
A294: F-011 | B294: Puesta en servicio: prueba de presión, hermeticidad y lavado del sistema de hidrantes | C294: LOTE | D294: 1 | E294: 0 | F294: 4500 | G294: =E294+F294 -> 4500 | H294: =ROUND(D294*G294,2) -> 4500
A295: F-012 | B295: Tubería de acero galvanizado por inmersión en caliente, DN150, sistema de acoplamiento ranurado | C295: ML | D295: 200 | E295: 54 | F295: 35 | G295: =E295+F295 -> 89 | H295: =ROUND(D295*G295,2) -> 17800
... A334: F-051 | B334: Desmantelamiento y disposición de tubería y dispositivos de protección contra incendio existentes | C334: LOTE | D334: 1 | E334: 0 | F334: 4800 | G334: =E334+F334 -> 4800 | H334: =ROUND(D334*G334,2) -> 4800
A335: F TOTAL | B335: SUBTOTAL SECCIÓN F — 06 PROTECCIÓN CONTRA INCENDIO Y ALARMA | H335: =SUM(H284:H334) -> 150728.24
A337: SECCIÓN G — 07 SISTEMAS DE TI, CCTV Y CONTROL DE ACCESO
A338: G-001 | B338: Cámara de red tipo bala infrarroja de interior, 4 MP o superior, WDR, entrada de audio, DC12V y PoE, con soporte de montaje | C338: PZA | D338: 8 | E338: 265 | F338: 98 | G338: =E338+F338 -> 363 | H338: =ROUND(D338*G338,2) -> 2904
A339: G-002 | B339: Charola tipo canal, 200x100 mm, para sistemas de baja tensión | C339: ML | D339: 60 | E339: 33 | F339: 19 | G339: =E339+F339 -> 52 | H339: =ROUND(D339*G339,2) -> 3120
A340: G-003 | B340: Cable de red categoría 6, CAT.6 | C340: ML | D340: 600 | E340: 1.5 | F340: 1.15 | G340: =E340+F340 -> 2.65 | H340: =ROUND(D340*G340,2) -> 1590
A341: G-004 | B341: Tubo conduit de acero JDG25 (equivalente EMT 1") | C341: ML | D341: 80 | E341: 4.3 | F341: 5.3 | G341: =E341+F341 -> 9.6 | H341: =ROUND(D341*G341,2) -> 768
A342: G-005 | B342: Caja de conexión, tipo 86 | C342: PZA | D342: 8 | E342: 4.4 | F342: 5.7 | G342: =E342+F342 -> 10.1 | H342: =ROUND(D342*G342,2) -> 80.8
...

Sheet 6. RESUMEN DE COSTOS
A1: LESTRAL CONSTRUCTORA, S. DE R.L. DE C.V. | ELECTROMECÁNICA DEL PACÍFICO (EMP)
A2: 6. RESUMEN DE COSTOS — TODAS LAS CIFRAS EN USD
B4: CONCEPTO | C4: TASA | D4: IMPORTE (USD) | E4: BASE DE CÁLCULO
B5: A. 01 PRELIMINARES Y MEDIDAS DE CONSTRUCCIÓN | D5: =SUMIF('5. DESGLOSE PARTIDAS'!$A:$A,"A TOTAL",'5. DESGLOSE PARTIDAS'!$H:$H) -> 266800 | E5: Suma de partidas cotizadas, hoja 5
B6: B. 02 ARQUITECTÓNICO, ESTRUCTURA Y ACABADOS | D6: =SUMIF('5. DESGLOSE PARTIDAS'!$A:$A,"B TOTAL",'5. DESGLOSE PARTIDAS'!$H:$H) -> 606786.77 | E6: Suma de partidas cotizadas, hoja 5
B7: C. 03 HVAC Y SISTEMAS DE AIRE DE CUARTO LIMPIO | D7: =SUMIF('5. DESGLOSE PARTIDAS'!$A:$A,"C TOTAL",'5. DESGLOSE PARTIDAS'!$H:$H) -> 365367 | E7: Suma de partidas cotizadas, hoja 5
B8: D. 04 INSTALACIONES ELÉCTRICAS | D8: =SUMIF('5. DESGLOSE PARTIDAS'!$A:$A,"D TOTAL",'5. DESGLOSE PARTIDAS'!$H:$H) -> 275378.78 | E8: Suma de partidas cotizadas, hoja 5
B9: E. 05 HIDRÁULICA, AGUA POTABLE Y DRENAJE | D9: =SUMIF('5. DESGLOSE PARTIDAS'!$A:$A,"E TOTAL",'5. DESGLOSE PARTIDAS'!$H:$H) -> 62252.99 | E9: Suma de partidas cotizadas, hoja 5
B10: F. 06 PROTECCIÓN CONTRA INCENDIO Y ALARMA | D10: =SUMIF('5. DESGLOSE PARTIDAS'!$A:$A,"F TOTAL",'5. DESGLOSE PARTIDAS'!$H:$H) -> 150728.24 | E10: Suma de partidas cotizadas, hoja 5
B11: G. 07 SISTEMAS DE TI, CCTV Y CONTROL DE ACCESO | D11: =SUMIF('5. DESGLOSE PARTIDAS'!$A:$A,"G TOTAL",'5. DESGLOSE PARTIDAS'!$H:$H) -> 34987.99 | E11: Suma de partidas cotizadas, hoja 5
B12: H. 08 DISTRIBUCIÓN DE AIRE COMPRIMIDO | D12: =SUMIF('5. DESGLOSE PARTIDAS'!$A:$A,"H TOTAL",'5. DESGLOSE PARTIDAS'!$H:$H) -> 30317.09 | E12: Suma de partidas cotizadas, hoja 5
B13: A. COSTO DIRECTO TOTAL | D13: =SUM(D5:D12) -> 1792618.9 | E13: Material más instalación, las 341 partidas, puesto en obra e instalado
B14: B. COSTO INDIRECTO (oficina central, fianzas, financiamiento) | C14: 0.08 | D14: =ROUND(D13*C14,2) -> 143409.51 | E14: 8% sobre el costo directo. Los indirectos de campo (supervisión, seguros, instalaciones provisionales, servicios) ya están cotizados en la Sección A, por lo que esta tasa cubre únicamente oficina central y evita duplicidad.
B15: C. SUBTOTAL (directo + indirecto) | D15: =D13+D14 -> 1936028.4
B16: D. UTILIDAD DEL CONTRATISTA | C16: 0.1 | D16: =ROUND(D15*C16,2) -> 193602.84 | E16: 10% sobre el subtotal anterior, estándar para obra industrial llave en mano de esta escala en Baja California.
B17: E. SUBTOTAL (directo + indirecto + utilidad) | D17: =D15+D16 -> 2129631.2
B18: F. CONTINGENCIA | C18: 0.03 | D18: =ROUND(D17*C18,2) -> 63888.94 | E18: 3% sobre el subtotal anterior. Cubre variación de cantidades al verificar contra planos IFC y condiciones imprevistas menores del edificio existente. La contingencia no ejercida se devuelve al cliente en el finiquito.
B19: G. TOTAL ANTES DE IVA | D19: =D17+D18 -> 2193520.1 | E19: Precio contractual sin impuesto
B20: H. IVA | C20: 0.08 | D20: =ROUND(D19*C20,2) -> 175481.61 | E20: 8% conforme al estímulo fiscal de la Región Fronteriza Norte para Baja California
B21: I. PRECIO TOTAL DEL CONTRATO (IVA incluido) | D21: =D19+D20 -> 2369001.8
B23: DESGLOSE MATERIAL / INSTALACIÓN
B24: Procura de material y equipo | D24: =SUMPRODUCT('5. DESGLOSE PARTIDAS'!$D$6:$D$371,'5. DESGLOSE PARTIDAS'!$E$6:$E$371) -> 963504.39 | E24: Columna D x columna E, hoja 5
B25: Trabajos de construcción e instalación | D25: =SUMPRODUCT('5. DESGLOSE PARTIDAS'!$D$6:$D$371,'5. DESGLOSE PARTIDAS'!$F$6:$F$371) -> 829114.48 | E25: Columna D x columna F, hoja 5

Sheet 7. CONDICIONES COMERCIALES
A1: LESTRAL CONSTRUCTORA, S. DE R.L. DE C.V. | ELECTROMECÁNICA DEL PACÍFICO (EMP)
A2: 7. CONDICIONES COMERCIALES
B4: 7.1 ESQUEMA DE PAGOS
B5: HITO | C5: % DEL PRECIO | D5: IMPORTE (USD) | E5: CONDICIÓN DE LIBERACIÓN
B6: Anticipo a la firma del contrato (semana 1) | C6: 0.3 | D6: =ROUND('6. RESUMEN DE COSTOS'!$D$21*C6,2) -> 710700.53 | E6: Contrato u orden de compra firmada, factura y fianza de anticipo si aplica
B7: Estimación 1 - estructura y muros (semana 7) | C7: 0.2 | D7: =ROUND('6. RESUMEN DE COSTOS'!$D$21*C7,2) -> 473800.35 | E7: Avance certificado, factura y reporte fotográfico
B8: Estimación 2 - instalación gruesa MEP terminada (semana 13) | C8: 0.25 | D8: =ROUND('6. RESUMEN DE COSTOS'!$D$21*C8,2) -> 592250.44 | E8: Avance certificado, factura y liberación de inspección de instalación gruesa
B9: Estimación 3 - acabados y equipos colocados (semana 18) | C9: 0.15 | D9: =ROUND('6. RESUMEN DE COSTOS'!$D$21*C9,2) -> 355350.26 | E9: Avance certificado, factura y reportes de pruebas
B10: Finiquito contra entrega y aceptación (semana 24) | C10: 0.1 | D10: =ROUND('6. RESUMEN DE COSTOS'!$D$21*C10,2) -> 236900.18 | E10: Acta de entrega-recepción, dossier de cierre y factura
B11: TOTAL | C11: =SUM(C6:C10) -> 1 | D11: =SUM(D6:D10) -> 2369001.8
B13: 7.2 VIGENCIA DE LA OFERTA Y MONEDA
B14: • Vigencia: 30 días naturales a partir del 10 de septiembre de 2026. Después de esa fecha los precios quedan sujetos a revisión contra las cotizaciones de proveedor vigentes.
B15: • Moneda: dólares americanos (USD). Todos los pagos se realizan en USD. Cuando se requiere tipo de cambio de referencia para insumos en pesos, se utilizó 17.00 MXN/USD, que se reconsidera a la firma del contrato.
B16: • Los precios son unitarios, firmes durante la vigencia, e incluyen material, mano de obra, equipo, herramienta, transporte, supervisión e indirectos de campo, puesto en obra e instalado.
B17: • Aplica IVA del 8% conforme al estímulo fiscal de la Región Fronteriza Norte para Baja California y se muestra por separado en el resumen de costos.
B19: 7.3 ANTICIPO Y ESTIMACIONES
B20: • Anticipo: 30% del precio del contrato a la firma, contra factura y, si el cliente lo requiere, fianza de anticipo emitida por afianzadora mexicana.
B21: • El anticipo se amortiza proporcionalmente en cada estimación de avance posterior.
B22: • Las estimaciones de avance se presentan mensualmente, certificadas de manera conjunta por el representante del cliente y el superintendente de EMP, soportadas con cantidades medidas y reporte fotográfico.
B23: • Plazo de pago: 7 días hábiles a partir de la aceptación de la estimación certificada y la recepción de factura válida. Finiquito: 10 días hábiles.
B24: • Retención: el cliente puede retener 5% de cada estimación, liberable contra el acta de entrega-recepción, o sustituirla por fianza de cumplimiento de valor equivalente.
B26: 7.4 GARANTÍAS
... B49: Lestral Constructora / Electromecánica del Pacífico (EMP) — Responsable técnico y punto único de contacto

Sheet 8. PROGRAMA GANTT
A1: LESTRAL CONSTRUCTORA, S. DE R.L. DE C.V. | ELECTROMECÁNICA DEL PACÍFICO (EMP)
A2: 8. PROGRAMA DE OBRA — GANTT SEMANAL CON RUTA CRÍTICA E HITOS
B4: Duración 24 semanas a partir del anticipo. Simbología: ■ ruta crítica ■ actividad no crítica ◆ hito ▲ hito de pago
B6: # | C6: ACTIVIDAD | D6: RUTA | E6: 1 | F6: 2 | G6: 3 | H6: 4 | I6: 5 | J6: 6 | K6: 7 | L6: 8 | M6: 9 | N6: 10 | O6: 11 | P6: 12 | Q6: 13 | R6: 14 | S6: 15 | T6: 16 | U6: 17 | V6: 18 | W6: 19 | X6: 20 | Y6: 21 | Z6: 22 | AA6: 23 | AB6: 24
B7: 1 | C7: Adjudicación, movilización y entrega de submittals | D7: RC
B8: 2 | C8: Procura de equipo de largo plazo (VRF, UMA de expansión directa, tableros, transformador) | D8: RC
B9: 3 | C9: Planos de taller y adecuación normativa NOM | D9: RC
B10: 4 | C10: Demolición y desmantelamiento de instalaciones existentes | D10: RC
B11: 5 | C11: Ranurado en muro y piso, barrenos | D11: —
B12: 6 | C12: Fabricación en taller de estructura metálica | D12: —
B13: 7 | C13: Montaje de estructura metálica | D13: RC
B14: 8 | C14: Muros de block y albañilería | D14: —
B15: 9 | C15: Instalación gruesa de ductos HVAC | D15: RC
B16: 10 | C16: Tubería de refrigerante y condensados | D16: —
B17: 11 | C17: Instalación gruesa de charola, conduit y cableado | D17: —
B18: 12 | C18: Tubería de rociadores e hidrantes | D18: —
... B32: 26 | C32: Lista de detalles, limpieza fina, as-builts y entrega | D32: RC
B34: HITOS DEL PROYECTO
B35: H1 Adjudicación y anticipo | E35: ◆
B36: H2 Planos de taller aprobados | H36: ◆
B37: H3 Estructura y muros terminados | R37: ◆
B38: H4 Instalación gruesa MEP terminada | T38: ◆
B39: H5 Energización y arranque de equipos | W39: ◆
B40: H6 Puesta en servicio terminada | Y40: ◆
B41: H7 Terminación sustancial y entrega | AB41: ◆
B43: HITOS DE PAGO
B44: Anticipo a la firma del contrato (30%) | E44: ▲
B45: Estimación 1 - estructura y muros (20%) | K45: ▲
B46: Estimación 2 - instalación gruesa MEP terminada (25%) | Q46: ▲
B47: Estimación 3 - acabados y equipos colocados (15%) | V47: ▲
B48: Finiquito contra entrega y aceptación (10%) | AB48: ▲
B50: Ruta crítica: adjudicación y movilización → procura de equipo de largo plazo → planos de taller y adecuación NOM → demolición → montaje de estructura → instalación gruesa de ductos HVAC → muro de panel de cuarto limpio → plafón de panel de cuarto limpio → colocación de equipos HVAC → piso epóxico → puesta en servicio y balanceo → calificación de cuarto limpio → entrega. La procura de la condensadora de 123.5 kW, la manejadora de expansión directa y el transformador de 200 kVA gobierna las primeras diez semanas; las medidas de Ingeniería de Valor de la hoja 9 sacan de esa ruta crítica al transformador y a los materiales de consumo importados.

Sheet 9. INGENIERIA DE VALOR
A1: LESTRAL CONSTRUCTORA, S. DE R.L. DE C.V. | ELECTROMECÁNICA DEL PACÍFICO (EMP)
A2: 9. INGENIERÍA DE VALOR PROPUESTA POR EMP
B4: La cotización base cotiza el proyecto ejecutivo exactamente como está diseñado. Las alternativas siguientes son propuestas de EMP; ninguna se aplicó al precio base. Cada una se cuantifica por separado para que el cliente la acepte o rechace por sus propios méritos. Los ahorros se calculan sobre las partidas afectadas de la hoja 5.
B7: 9.1 ALTERNATIVAS DE REDUCCIÓN DE COSTO
B8: REF | C8: ALTERNATIVA | D8: IMPACTO EN PLAZO | E8: AHORRO ESTIMADO (USD) | F8: IMPACTO EN DESEMPEÑO
B9: VE-01 | C9: Reespecificar equipos y tableros a 480/277-220 V, 60 Hz (NEMA/NOM) y eliminar el transformador de 200 kVA 480/380 V | D9: -2 semanas | E9: 15400 | F9: Cumplimiento nativo de NOM-001-SEDE; elimina ~2% de pérdidas por transformación y un punto único de falla; refacciones locales en vez de importadas
B10: VE-02 | C10: Sustituir canalización, conductor y tubería hidráulica de norma GB por equivalentes norteamericanos (JDG/SC a EMT/RMC, cable GB a THHN/XHHW, PP-R a CPVC) | D10: -4 semanas | E10: 13287.63 | F10: Desempeño igual o superior, con listado UL y certificación NOM; elimina 8-12 semanas de importación y la exposición aduanal en materiales de consumo
B11: VE-03 | C11: Convertir el diseño contra incendio GB a cálculo hidráulico NFPA 13 / NFPA 14 con rociadores K5.6 y una sola columna combinada para rociadores e hidrantes | D11: -1 semanas | E11: 13295.04 | F11: Diseño asegurable (FM/NFPA) aceptado por la autoridad mexicana y por la aseguradora de la planta; elimina el riesgo de reinspección y retrabajo de una entrega solo GB
B12: VE-04 | C12: Limitar el plafón sándwich transitable de cuarto limpio a las áreas clasificadas; plafón suspendido estándar en oficinas, vestidor y áreas de apoyo | D12: -1 semanas | E12: 20302.49 | F12: Sin efecto en la clasificación ISO: las áreas afectadas están fuera de la envolvente clasificada y no tienen requisito de cascada de presión
B13: VE-05 | C13: Aplicar epóxico ESD únicamente en las áreas con requisito electrostático declarado; epóxico estándar en el resto | D13: neutro | E13: 6948.02 | F13: Requiere confirmación por escrito del límite de la zona ESD por parte del cliente; el desempeño ESD no cambia dentro de la zona declarada
B14: VE-06 | C14: Utilizar ducto de panel fenólico preaislado en los tramos de aire exterior y extracción no clasificados, en vez de ducto galvanizado con aislamiento exterior | D14: -1 semanas | E14: 2136.42 | F14: Menor clase de fuga y mejor desempeño térmico; se fabrica en sitio, lo que saca la cola del taller de lámina de la ruta crítica
B15: VE-07 | C15: Liberar la provisión de trabajo nocturno y aceleración a cambio de acceso al sitio 24 horas y frente de trabajo libre | D15: neutro | E15: 9500 | F15: Requiere que el cliente otorgue acceso sin restricción; si el acceso permanece limitado a un turno, la provisión debe restituirse
B16: Σ | C16: AHORRO TOTAL IDENTIFICADO SOBRE COSTO DIRECTO | D16: -4 semanas | E16: =SUM(E9:E15) -> 80869.6
B18: 9.2 ALTERNATIVAS DE DESEMPEÑO (costo de capital adicional, reducción de costo de operación)
B19: REF | C19: ALTERNATIVA | D19: CAPEX ADICIONAL (USD) | E19: AHORRO ANUAL DE OPERACIÓN (USD) | F19: IMPACTO EN DESEMPEÑO
B20: VE-08 | C20: Banco VRF con recuperación de calor en lugar de dos unidades condensadoras independientes | D20: 11500 | E20: 8600 | F20: Transfiere calor entre zonas que piden frío y calor de forma simultánea; retorno aproximado de 1.3 años
B21: VE-09 | C21: Rueda entálpica de recuperación en la unidad de aire exterior de 2,500 m3/h | D21: 6800 | E21: 5400 | F21: Recupera aproximadamente el 65% de la carga entálpica de aire exterior; retorno aproximado de 1.3 años y reduce la demanda pico
B22: VE-10 | C22: Control de atenuación 0-10 V y sensores de ocupación en el alumbrado de áreas no clasificadas | D22: 0 | E22: 3200 | F22: Sin impacto de costo de capital si se especifica desde la compra; reduce el consumo de alumbrado aproximadamente 35% en áreas de ocupación intermitente
B23: Σ | C23: TOTAL | D23: =SUM(D20:D22) -> 18300 | E23: =SUM(E20:E22) -> 17200
B25: Recomendación de EMP: VE-01, VE-02 y VE-03 deben tratarse como asuntos de cumplimiento y no como ahorros opcionales. La tensión de distribución de 380 V no existe en la red mexicana, y el diseño contra incendio GB no es la base sobre la cual la autoridad local o la aseguradora de planta aprobarán la instalación. Adoptar las tres en conjunto saca de la ruta crítica al transformador, a los materiales de consumo importados y al riesgo de reingreso de trámite, y es el mayor contribuyente individual tanto a la reducción de costo como a la de plazo que se muestra en la hoja 10.

Sheet 10. BASE VS OPTIMIZADO
A1: LESTRAL CONSTRUCTORA, S. DE R.L. DE C.V. | ELECTROMECÁNICA DEL PACÍFICO (EMP)
A2: 10. COMPARATIVO DE ESCENARIOS — ESCENARIO BASE VS ESCENARIO OPTIMIZADO
B4: Escenario base: el proyecto ejecutivo cotizado exactamente como está diseñado. Escenario optimizado: el escenario base con las siete alternativas de reducción de costo de la hoja 9.1 adoptadas.
B6: CONCEPTO | C6: ESCENARIO BASE | D6: ESCENARIO OPTIMIZADO | E6: DIFERENCIA
B7: Costo directo | C7: ='6. RESUMEN DE COSTOS'!D13 -> 1792618.9 | D7: =C7-'9. INGENIERIA DE VALOR'!E16 -> 1711749.3 | E7: =D7-C7 -> -80869.6
B8: Costo indirecto (8%) | C8: =ROUND(C7*'6. RESUMEN DE COSTOS'!C14,2) -> 143409.51 | D8: =ROUND(D7*'6. RESUMEN DE COSTOS'!C14,2) -> 136939.94 | E8: =D8-C8 -> -6469.57
B9: Utilidad (10%) | C9: =ROUND((C7+C8)*'6. RESUMEN DE COSTOS'!C16,2) -> 193602.84 | D9: =ROUND((D7+D8)*'6. RESUMEN DE COSTOS'!C16,2) -> 184868.92 | E9: =D9-C9 -> -8733.92
B10: Contingencia (3%) | C10: =ROUND((C7+C8+C9)*'6. RESUMEN DE COSTOS'!C18,2) -> 63888.94 | D10: =ROUND((D7+D8+D9)*'6. RESUMEN DE COSTOS'!C18,2) -> 61006.74 | E10: =D10-C10 -> -2882.2
B11: TOTAL ANTES DE IVA | C11: =C7+C8+C9+C10 -> 2193520.1 | D11: =D7+D8+D9+D10 -> 2094564.9 | E11: =D11-C11 -> -98955.29
B12: IVA 8% | C12: =ROUND(C11*'6. RESUMEN DE COSTOS'!C20,2) -> 175481.61 | D12: =ROUND(D11*'6. RESUMEN DE COSTOS'!C20,2) -> 167565.19 | E12: =D12-C12 -> -7916.42
B13: PRECIO TOTAL DEL CONTRATO | C13: =C11+C12 -> 2369001.8 | D13: =D11+D12 -> 2262130 | E13: =D13-C13 -> -106871.71
B14: Ahorro como % del precio del contrato | C14: 0 | D14: =-E13/C13 -> 0.04511255 | E14: =D14 -> 0.04511255
B15: Plazo de construcción (semanas) | C15: 24 | D15: 20 | E15: -4
B16: Ahorro anual de operación (si se adopta 9.2) | C16: 0 | D16: ='9. INGENIERIA DE VALOR'!E23 -> 17200 | E16: =D16 -> 17200
B18: BENEFICIOS DEL ESCENARIO OPTIMIZADO
B19: • Los equipos operan a una tensión de distribución que sí existe en México, por lo que refacciones, servicio y ampliaciones futuras se consiguen localmente en vez de importarse.
B20: • El transformador de 200 kVA desaparece del cuarto eléctrico, junto con sus pérdidas permanentes, su espacio ocupado y sus 10 a 12 semanas de entrega.
B21: • Los materiales de consumo (tubería conduit, conductor, tubería hidráulica) pasan a tener listado UL y certificación NOM, lo que saca de la ruta crítica la exposición aduanal y de tiempo de entrega.
B22: • El sistema de protección contra incendio se vuelve asegurable en base NFPA, que es lo que en realidad revisarán tanto la autoridad mexicana como la aseguradora de planta.
B23: • Se recuperan cuatro semanas de la ruta crítica, lo que adelanta el arranque de producción aproximadamente un mes.
B24: • La clasificación del cuarto limpio, la cascada de presión, los cambios de aire por hora y el desempeño ESD dentro de la zona declarada no cambian en ningún aspecto.

Sheet 11. FORMATO BOQ CLIENTE
A1: LESTRAL CONSTRUCTORA, S. DE R.L. DE C.V. | ELECTROMECÁNICA DEL PACÍFICO (EMP)
A2: 11. RESUMEN DE COSTOS MAPEADO AL FORMATO DEL BOQ DEL CLIENTE (hoja 01.Summary)
B4: El mismo precio, presentado en la estructura de resumen del propio cliente para que ambos documentos se concilien línea por línea.
B6: No. | C6: DESCRIPCIÓN DE LA PARTIDA | D6: CONSTRUCCIÓN E INSTALACIÓN (USD) | E6: PROCURA DE EQUIPO (USD) | F6: COSTO TOTAL (USD)
B7: 1 | C7: Costo de medidas de construcción | D7: =SUMPRODUCT('5. DESGLOSE PARTIDAS'!$D$7:$D$28,'5. DESGLOSE PARTIDAS'!$F$7:$F$28) -> 266800 | E7: =SUMPRODUCT('5. DESGLOSE PARTIDAS'!$D$7:$D$28,'5. DESGLOSE PARTIDAS'!$E$7:$E$28) -> 0 | F7: =D7+E7 -> 266800
B8: 2 | C8: Arquitectónico y acabados | D8: =SUMPRODUCT('5. DESGLOSE PARTIDAS'!$D$32:$D$62,'5. DESGLOSE PARTIDAS'!$F$32:$F$62) -> 198570.57 | E8: =SUMPRODUCT('5. DESGLOSE PARTIDAS'!$D$32:$D$62,'5. DESGLOSE PARTIDAS'!$E$32:$E$62) -> 408216.21 | F8: =D8+E8 -> 606786.78
B9: 3 | C9: Obra de HVAC | D9: =SUMPRODUCT('5. DESGLOSE PARTIDAS'!$D$66:$D$176,'5. DESGLOSE PARTIDAS'!$F$66:$F$176) -> 121764.52 | E9: =SUMPRODUCT('5. DESGLOSE PARTIDAS'!$D$66:$D$176,'5. DESGLOSE PARTIDAS'!$E$66:$E$176) -> 243602.47 | F9: =D9+E9 -> 365366.99
B10: 4 | C10: Obra hidrosanitaria | D10: =SUMPRODUCT('5. DESGLOSE PARTIDAS'!$D$246:$D$280,'5. DESGLOSE PARTIDAS'!$F$246:$F$280) -> 26629.037 | E10: =SUMPRODUCT('5. DESGLOSE PARTIDAS'!$D$246:$D$280,'5. DESGLOSE PARTIDAS'!$E$246:$E$280) -> 35623.958 | F10: =D10+E10 -> 62252.995
B11: 5 | C11: Obra de protección contra incendio | D11: =SUMPRODUCT('5. DESGLOSE PARTIDAS'!$D$284:$D$334,'5. DESGLOSE PARTIDAS'!$F$284:$F$334) -> 74581.988 | E11: =SUMPRODUCT('5. DESGLOSE PARTIDAS'!$D$284:$D$334,'5. DESGLOSE PARTIDAS'!$E$284:$E$334) -> 76146.258 | F11: =D11+E11 -> 150728.25
B12: 6 | C12: Obra eléctrica | D12: =SUMPRODUCT('5. DESGLOSE PARTIDAS'!$D$180:$D$242,'5. DESGLOSE PARTIDAS'!$F$180:$F$242) -> 112676.91 | E12: =SUMPRODUCT('5. DESGLOSE PARTIDAS'!$D$180:$D$242,'5. DESGLOSE PARTIDAS'!$E$180:$E$242) -> 162701.87 | F12: =D12+E12 -> 275378.79
B13: 7 | C13: Obra de baja tensión | D13: =SUMPRODUCT('5. DESGLOSE PARTIDAS'!$D$338:$D$357,'5. DESGLOSE PARTIDAS'!$F$338:$F$357) -> 17064.51 | E13: =SUMPRODUCT('5. DESGLOSE PARTIDAS'!$D$338:$D$357,'5. DESGLOSE PARTIDAS'!$E$338:$E$357) -> 17923.479 | F13: =D13+E13 -> 34987.988
B14: 8 | C14: Obra de aire comprimido | D14: =SUMPRODUCT('5. DESGLOSE PARTIDAS'!$D$361:$D$368,'5. DESGLOSE PARTIDAS'!$F$361:$F$368) -> 11026.943 | E14: =SUMPRODUCT('5. DESGLOSE PARTIDAS'!$D$361:$D$368,'5. DESGLOSE PARTIDAS'!$E$361:$E$368) -> 19290.147 | F14: =D14+E14 -> 30317.09
B15: 9 | C15: Flete y logística | D15: 0 | E15: 0 | F15: Incluido en los precios unitarios; no se lleva flete de importación por separado
B16: 10 | C16: Pedimento y gastos aduanales | D16: 0 | E16: 0 | F16: No aplica: los materiales se adquieren en el mercado nacional
B17: 11 | C17: Honorarios de administración del proyecto | D17: ='6. RESUMEN DE COSTOS'!D14+'6. RESUMEN DE COSTOS'!D16+'6. RESUMEN DE COSTOS'!D18 -> 400901.29 | E17: 0 | F17: =D17+E17 -> 400901.29
B18: 12 | C18: Subtotal antes de IVA | D18: =SUM(D7:D17) -> 1230015.8 | E18: =SUM(E7:E17) -> 963504.39 | F18: =D18+E18 -> 2193520.2
B19: 13 | C19: IVA 8% | F19: =ROUND(F18*'6. RESUMEN DE COSTOS'!C20,2) -> 175481.61
B20: 14 | C20: PRECIO TOTAL (USD) | F20: =F18+F19 -> 2369001.8
B22: La línea 11 concentra el costo indirecto, la utilidad y la contingencia de la hoja 6 agrupados como honorario de administración del proyecto, que es el equivalente más cercano en la plantilla del cliente. El total de la línea 14 es idéntico al precio total del contrato de la hoja 6.
